gbp_feeds-1.1.0.dist-info/METADATA
gbp_feeds-1.1.0.dist-info/WHEEL
gbp_feeds-1.1.0.dist-info/entry_points.txt
gbp_feeds-1.1.0.dist-info/licenses/LICENSE
gbp_feeds/__init__.py
gbp_feeds/django/__init__.py
gbp_feeds/django/gbp_feeds/__init__.py
gbp_feeds/django/gbp_feeds/apps.py
gbp_feeds/django/gbp_feeds/templates/gbp_feeds/build.html
gbp_feeds/django/gbp_feeds/templates/gentoo_build_publisher/base.html
gbp_feeds/django/gbp_feeds/templates/gentoo_build_publisher/machine/buildcard.html
gbp_feeds/django/gbp_feeds/templatetags/__init__.py
gbp_feeds/django/gbp_feeds/templatetags/url_tags.py
gbp_feeds/django/gbp_feeds/views/__init__.py
gbp_feeds/django/gbp_feeds/views/utils.py
gbp_feeds/py.typed
gbp_feeds/settings.py
gbp_feeds-1.1.0.dist-info/RECORD
