Metadata-Version: 2.1
Name: gbp-feeds
Version: 1.1.0
Summary: Publish Atom/RSS feeds for Gentoo Build Publisher
Author-Email: Albert Hopkins <marduk@letterboxes.org>
License: GPL3+
Project-URL: homepage, https://github.com/enku/gbp-feeds
Project-URL: repository, https://github.com/enku/gbp-feeds
Requires-Python: >=3.12
Requires-Dist: gentoo-build-publisher>=3.3.0
Requires-Dist: django>=5.2.4
Requires-Dist: feedgenerator>=2.2.0
Requires-Dist: gbpcli>=3.0.1
Requires-Dist: yarl>=1.20.1
